[[{"t":"having ","n":"having","w":0,"g":5875},{"t":"it ","n":"it","w":0,"g":5876}],[{"t":"having ","n":"having","w":1,"g":18800},{"t":"it ","n":"it","w":1,"g":18801}],[{"t":"having ","n":"having","w":2,"g":31800},{"t":"it ","n":"it","w":2,"g":31801}],[{"t":"having ","n":"having","w":3,"g":45134},{"t":"it ","n":"it","w":3,"g":45135}],[{"t":"having ","n":"having","w":4,"g":59241},{"t":"this ","n":"this","w":4,"g":59242},{"t":"part ","n":"part","w":4,"g":59243}],[{"t":"has ","n":"has","w":5,"g":73505},{"t":"this ","n":"this","w":5,"g":73506},{"t":"part ","n":"part","w":5,"g":73507}]]