[[{"t":"seems ","n":"seems","w":2,"g":29187},{"t":"to ","n":"to","w":2,"g":29188},{"t":"me ","n":"me","w":2,"g":29189},{"t":"to ","n":"to","w":2,"g":29190},{"t":"be ","n":"be","w":2,"g":29191},{"t":"the ","n":"the","w":2,"g":29192},{"t":"case","n":"case","w":2,"g":29193},{"t":", ","n":",","w":2,"g":29194},{"t":"what ","n":"what","w":2,"g":29195},{"t":"does ","n":"does","w":2,"g":29196},{"t":"it ","n":"it","w":2,"g":29197},{"t":"show","n":"show","w":2,"g":29198},{"t":", ","n":",","w":2,"g":29199},{"t":"but ","n":"but","w":2,"g":29200}],[{"t":"has ","n":"has","w":4,"g":56528},{"t":"hitherto ","n":"hitherto","w":4,"g":56529},{"t":"been ","n":"been","w":4,"g":56530},{"t":"supposed","n":"supposed","w":4,"g":56531},{"t":". ","n":".","w":4,"g":56532},{"t":"The ","n":"the","w":4,"g":56533},{"t":"lake","n":"lake","w":4,"g":56534},{"t":"-","n":"-","w":4,"g":56535},{"t":"inhabitants ","n":"inhabitants","w":4,"g":56536},{"t":"of ","n":"of","w":4,"g":56537},{"t":"Switzerland ","n":"switzerland","w":4,"g":56538},{"t":"cultivated ","n":"cultivated","w":4,"g":56539},{"t":"several ","n":"several","w":4,"g":56540},{"t":"kinds ","n":"kinds","w":4,"g":56541},{"t":"of ","n":"of","w":4,"g":56542},{"t":"wheat ","n":"wheat","w":4,"g":56543},{"t":"and ","n":"and","w":4,"g":56544},{"t":"barley","n":"barley","w":4,"g":56545},{"t":", ","n":",","w":4,"g":56546},{"t":"the ","n":"the","w":4,"g":56547},{"t":"pea","n":"pea","w":4,"g":56548},{"t":", ","n":",","w":4,"g":56549},{"t":"the ","n":"the","w":4,"g":56550},{"t":"poppy ","n":"poppy","w":4,"g":56551},{"t":"for ","n":"for","w":4,"g":56552},{"t":"oil","n":"oil","w":4,"g":56553},{"t":", ","n":",","w":4,"g":56554},{"t":"and ","n":"and","w":4,"g":56555},{"t":"flax","n":"flax","w":4,"g":56556},{"t":"; ","n":";","w":4,"g":56557},{"t":"and ","n":"and","w":4,"g":56558},{"t":"they ","n":"they","w":4,"g":56559},{"t":"possessed ","n":"possessed","w":4,"g":56560},{"t":"several ","n":"several","w":4,"g":56561},{"t":"domesticated ","n":"domesticated","w":4,"g":56562},{"t":"animals","n":"animals","w":4,"g":56563},{"t":"; ","n":";","w":4,"g":56564},{"t":"they ","n":"they","w":4,"g":56565},{"t":"had ","n":"had","w":4,"g":56566},{"t":"also ","n":"also","w":4,"g":56567},{"t":"commerce ","n":"commerce","w":4,"g":56568},{"t":"with ","n":"with","w":4,"g":56569},{"t":"other ","n":"other","w":4,"g":56570},{"t":"nations","n":"nations","w":4,"g":56571},{"t":". ","n":".","w":4,"g":56572},{"t":"All ","n":"all","w":4,"g":56573},{"t":"this ","n":"this","w":4,"g":56574},{"t":"clearly ","n":"clearly","w":4,"g":56575},{"t":"shows","n":"shows","w":4,"g":56576},{"t":", ","n":",","w":4,"g":56577},{"t":"as ","n":"as","w":4,"g":56578},{"t":"Heer ","n":"heer","w":4,"g":56579},{"t":"has ","n":"has","w":4,"g":56580},{"t":"remarked","n":"remarked","w":4,"g":56581},{"t":", ","n":",","w":4,"g":56582}],[{"t":"has ","n":"has","w":5,"g":70855},{"t":"hitherto ","n":"hitherto","w":5,"g":70856},{"t":"been ","n":"been","w":5,"g":70857},{"t":"supposed","n":"supposed","w":5,"g":70858},{"t":". ","n":".","w":5,"g":70859},{"t":"The ","n":"the","w":5,"g":70860},{"t":"lake","n":"lake","w":5,"g":70861},{"t":"-","n":"-","w":5,"g":70862},{"t":"inhabitants ","n":"inhabitants","w":5,"g":70863},{"t":"of ","n":"of","w":5,"g":70864},{"t":"Switzerland ","n":"switzerland","w":5,"g":70865},{"t":"cultivated ","n":"cultivated","w":5,"g":70866},{"t":"several ","n":"several","w":5,"g":70867},{"t":"kinds ","n":"kinds","w":5,"g":70868},{"t":"of ","n":"of","w":5,"g":70869},{"t":"wheat ","n":"wheat","w":5,"g":70870},{"t":"and ","n":"and","w":5,"g":70871},{"t":"barley","n":"barley","w":5,"g":70872},{"t":", ","n":",","w":5,"g":70873},{"t":"the ","n":"the","w":5,"g":70874},{"t":"pea","n":"pea","w":5,"g":70875},{"t":", ","n":",","w":5,"g":70876},{"t":"the ","n":"the","w":5,"g":70877},{"t":"poppy ","n":"poppy","w":5,"g":70878},{"t":"for ","n":"for","w":5,"g":70879},{"t":"oil","n":"oil","w":5,"g":70880},{"t":", ","n":",","w":5,"g":70881},{"t":"and ","n":"and","w":5,"g":70882},{"t":"flax","n":"flax","w":5,"g":70883},{"t":"; ","n":";","w":5,"g":70884},{"t":"and ","n":"and","w":5,"g":70885},{"t":"they ","n":"they","w":5,"g":70886},{"t":"possessed ","n":"possessed","w":5,"g":70887},{"t":"several ","n":"several","w":5,"g":70888},{"t":"domesticated ","n":"domesticated","w":5,"g":70889},{"t":"animals","n":"animals","w":5,"g":70890},{"t":". ","n":".","w":5,"g":70891},{"t":"They ","n":"they","w":5,"g":70892},{"t":"also ","n":"also","w":5,"g":70893},{"t":"carried ","n":"carried","w":5,"g":70894},{"t":"on ","n":"on","w":5,"g":70895},{"t":"commerce ","n":"commerce","w":5,"g":70896},{"t":"with ","n":"with","w":5,"g":70897},{"t":"other ","n":"other","w":5,"g":70898},{"t":"nations","n":"nations","w":5,"g":70899},{"t":". ","n":".","w":5,"g":70900},{"t":"All ","n":"all","w":5,"g":70901},{"t":"this ","n":"this","w":5,"g":70902},{"t":"clearly ","n":"clearly","w":5,"g":70903},{"t":"shows","n":"shows","w":5,"g":70904},{"t":", ","n":",","w":5,"g":70905},{"t":"as ","n":"as","w":5,"g":70906},{"t":"Heer ","n":"heer","w":5,"g":70907},{"t":"has ","n":"has","w":5,"g":70908},{"t":"remarked","n":"remarked","w":5,"g":70909},{"t":", ","n":",","w":5,"g":70910}],[{"t":"has ","n":"has","w":3,"g":42367},{"t":"hitherto ","n":"hitherto","w":3,"g":42368},{"t":"been ","n":"been","w":3,"g":42369},{"t":"supposed","n":"supposed","w":3,"g":42370},{"t":". ","n":".","w":3,"g":42371},{"t":"The ","n":"the","w":3,"g":42372},{"t":"lake","n":"lake","w":3,"g":42373},{"t":"-","n":"-","w":3,"g":42374},{"t":"inhabitants ","n":"inhabitants","w":3,"g":42375},{"t":"of ","n":"of","w":3,"g":42376},{"t":"Switzerland ","n":"switzerland","w":3,"g":42377},{"t":"cultivated ","n":"cultivated","w":3,"g":42378},{"t":"several ","n":"several","w":3,"g":42379},{"t":"kinds ","n":"kinds","w":3,"g":42380},{"t":"of ","n":"of","w":3,"g":42381},{"t":"wheat ","n":"wheat","w":3,"g":42382},{"t":"and ","n":"and","w":3,"g":42383},{"t":"barley","n":"barley","w":3,"g":42384},{"t":", ","n":",","w":3,"g":42385},{"t":"the ","n":"the","w":3,"g":42386},{"t":"pea","n":"pea","w":3,"g":42387},{"t":", ","n":",","w":3,"g":42388},{"t":"the ","n":"the","w":3,"g":42389},{"t":"poppy ","n":"poppy","w":3,"g":42390},{"t":"for ","n":"for","w":3,"g":42391},{"t":"oil","n":"oil","w":3,"g":42392},{"t":", ","n":",","w":3,"g":42393},{"t":"and ","n":"and","w":3,"g":42394},{"t":"flax","n":"flax","w":3,"g":42395},{"t":"; ","n":";","w":3,"g":42396},{"t":"and ","n":"and","w":3,"g":42397},{"t":"they ","n":"they","w":3,"g":42398},{"t":"possessed ","n":"possessed","w":3,"g":42399},{"t":"several ","n":"several","w":3,"g":42400},{"t":"domesticated ","n":"domesticated","w":3,"g":42401},{"t":"animals","n":"animals","w":3,"g":42402},{"t":"; ","n":";","w":3,"g":42403},{"t":"they ","n":"they","w":3,"g":42404},{"t":"had ","n":"had","w":3,"g":42405},{"t":"also ","n":"also","w":3,"g":42406},{"t":"commerce ","n":"commerce","w":3,"g":42407},{"t":"with ","n":"with","w":3,"g":42408},{"t":"other ","n":"other","w":3,"g":42409},{"t":"nations","n":"nations","w":3,"g":42410},{"t":". ","n":".","w":3,"g":42411},{"t":"All ","n":"all","w":3,"g":42412},{"t":"this ","n":"this","w":3,"g":42413},{"t":"clearly ","n":"clearly","w":3,"g":42414},{"t":"shows","n":"shows","w":3,"g":42415},{"t":", ","n":",","w":3,"g":42416},{"t":"as ","n":"as","w":3,"g":42417},{"t":"Heer ","n":"heer","w":3,"g":42418},{"t":"has ","n":"has","w":3,"g":42419},{"t":"remarked","n":"remarked","w":3,"g":42420},{"t":", ","n":",","w":3,"g":42421}]]